MiniumBoot/__init__.py
MiniumBoot/boot.py
MiniumBoot/driver.py
MiniumBoot/extractor.py
MiniumBoot/helpers.py
MiniumBoot/response_wrapper.py
MiniumBoot/validator.py
MiniumBoot-1.0.2.dist-info/METADATA
MiniumBoot-1.0.2.dist-info/WHEEL
MiniumBoot-1.0.2.dist-info/entry_points.txt
MiniumBoot-1.0.2.dist-info/top_level.txt
MiniumBoot-1.0.2.dist-info/RECORD
