Metadata-Version: 2.1
Name: MiniumBoot
Version: 1.0.2
Summary: MiniumBoot: make an easy way (yaml) to wechat miniprogram automation testing
Home-page: https://github.com/shigebeyond/MiniumBoot
Author: shigebeyond
Author-email: 772910474@qq.com
License: BSD
Classifier: Development Status :: 5 - Production/Stable
Classifier: Topic :: Software Development :: Testing
Classifier: Topic :: Software Development :: Quality Assurance
Classifier: Topic :: Software Development :: Libraries :: Python Modules
Classifier: Operating System :: POSIX :: Linux
Classifier: Operating System :: MacOS :: MacOS X
Classifier: Operating System :: Microsoft :: Windows
Classifier: Programming Language :: Python
Classifier: Programming Language :: Python :: 3.7
Classifier: Programming Language :: Python :: 3.8
Classifier: Programming Language :: Python :: 3.9
Requires-Python: >=3.6
Requires-Dist: lxml (==4.9.1)
Requires-Dist: pyutilb (>=1.0.5)
